{
    "AX": {
        "error": 0.006413703723039252,
        "error_type": "SEM",
        "filter_outliers_dict": {
            "filter_outliers": true,
            "iterations": 1,
            "std_devs": 2
        },
        "fit": "Average",
        "fn": 57,
        "include_baseline_error": false,
        "n": 60,
        "reviewed": true,
        "value": -0.02454882128043672
    },
    "CDD": {
        "error": 6.723079144112676e-06,
        "error_type": "SEM",
        "filter_outliers_dict": {
            "filter_outliers": true,
            "iterations": 1,
            "std_devs": 10
        },
        "fit": "Average",
        "fn": 60,
        "include_baseline_error": false,
        "n": 60,
        "reviewed": true,
        "value": 2.0255247363820672e-05
    },
    "H1": {
        "error": 0.005369289096916939,
        "error_type": "SEM",
        "filter_outliers_dict": {
            "filter_outliers": true,
            "iterations": 1,
            "std_devs": 2
        },
        "fit": "Average",
        "fn": 57,
        "include_baseline_error": false,
        "n": 60,
        "reviewed": true,
        "value": 0.018266670507983418
    },
    "H2": {
        "error": 0.015266849080857988,
        "error_type": "SEM",
        "filter_outliers_dict": {
            "filter_outliers": true,
            "iterations": 1,
            "std_devs": 2
        },
        "fit": "average",
        "value": 0.0552611648700632
    },
    "L1": {
        "error": 0.002376020145057778,
        "error_type": "SEM",
        "filter_outliers_dict": {
            "filter_outliers": true,
            "iterations": 1,
            "std_devs": 2
        },
        "fit": "Average",
        "fn": 59,
        "include_baseline_error": false,
        "n": 60,
        "reviewed": true,
        "value": -0.04090468798590414
    },
    "L2": {
        "error": 0.006081962923701559,
        "error_type": "SEM",
        "filter_outliers_dict": {
            "filter_outliers": true,
            "iterations": 1,
            "std_devs": 2
        },
        "fit": "Average",
        "fn": 59,
        "include_baseline_error": false,
        "n": 60,
        "reviewed": true,
        "value": -0.049679672422471566
    }
}