{
    "Ar36": {
        "error": 0.0006062860264994318,
        "error_type": "SEM",
        "filter_outliers_dict": {
            "filter_outliers": true,
            "iterations": 1,
            "std_devs": 2
        },
        "fit": "Linear",
        "fn": 59,
        "include_baseline_error": false,
        "n": 60,
        "reviewed": true,
        "value": 0.009086773617500234
    },
    "Ar37": {
        "error": 0.020893677486353637,
        "error_type": "SEM",
        "filter_outliers_dict": {
            "filter_outliers": true,
            "iterations": 1,
            "std_devs": 2
        },
        "fit": "Linear",
        "fn": 58,
        "include_baseline_error": false,
        "n": 60,
        "reviewed": true,
        "value": 1.4605134248081924
    },
    "Ar38": {
        "error": 0.011746661098429223,
        "error_type": "SEM",
        "filter_outliers_dict": {
            "filter_outliers": true,
            "iterations": 1,
            "std_devs": 2
        },
        "fit": "Linear",
        "fn": 57,
        "include_baseline_error": false,
        "n": 60,
        "reviewed": true,
        "value": -0.020729292549090853
    },
    "Ar39": {
        "error": 0.020146614962436287,
        "error_type": "SEM",
        "filter_outliers_dict": {
            "filter_outliers": true,
            "iterations": 1,
            "std_devs": 2
        },
        "fit": "Linear",
        "fn": 58,
        "include_baseline_error": false,
        "n": 60,
        "reviewed": true,
        "value": 0.449432802857869
    },
    "Ar40": {
        "error": 0.02415420439706104,
        "error_type": "SEM",
        "filter_outliers_dict": {
            "filter_outliers": true,
            "iterations": 1,
            "std_devs": 2
        },
        "fit": "Linear",
        "fn": 59,
        "include_baseline_error": false,
        "n": 60,
        "reviewed": true,
        "value": 12.587941687030497
    },
    "Ar41": {
        "error": 0.01764158122783458,
        "error_type": "SEM",
        "filter_outliers_dict": {
            "filter_outliers": true,
            "iterations": 1,
            "std_devs": 2
        },
        "fit": "Average",
        "value": 0.05175421058466869
    }
}